README.rst
setup.py
diff_py/VERSION
diff_py/__init__.py
diff_py/diff_helper.py
diff_py/requirements.txt
diff_py/runner.py
diff_py/test_diff_helper.py
diff_py/zdiff_helper.py
diff_py.egg-info/PKG-INFO
diff_py.egg-info/SOURCES.txt
diff_py.egg-info/dependency_links.txt
diff_py.egg-info/entry_points.txt
diff_py.egg-info/not-zip-safe
diff_py.egg-info/requires.txt
diff_py.egg-info/top_level.txt