Metadata-Version: 1.0
Name: diff-py
Version: 0.0.8
Summary: The simple diff tool which is written by Python. The diff result can be printed in console or to html file.
Home-page: http://www.github.com/askeing/diff_py
Author: Askeing Yen
Author-email: askeing@gmail.com
License: MPL
Keywords: diff html
Platform: UNKNOWN
